Workbook

Sheet Chart of Accounts
B2: CHART OF ACCOUNTS
B3: Account # | C3: Account Name | D3: Account Type | E3: Normal Balance | F3: Financial Statement
B4: 1000 | C4: Cash and Cash Equivalents | D4: Asset | E4: Debit | F4: Balance Sheet
B5: 1010 | C5: Petty Cash | D5: Asset | E5: Debit | F5: Balance Sheet
B6: 1100 | C6: Accounts Receivable | D6: Asset | E6: Debit | F6: Balance Sheet
B7: 1110 | C7: Allowance for Doubtful Accounts | D7: Contra-Asset | E7: Credit | F7: Balance Sheet
B8: 1200 | C8: Inventory | D8: Asset | E8: Debit | F8: Balance Sheet
B9: 1300 | C9: Prepaid Expenses | D9: Asset | E9: Debit | F9: Balance Sheet
B10: 1400 | C10: Short-term Investments | D10: Asset | E10: Debit | F10: Balance Sheet
B11: 1500 | C11: Property, Plant & Equipment | D11: Asset | E11: Debit | F11: Balance Sheet
B12: 1510 | C12: Accumulated Depreciation | D12: Contra-Asset | E12: Credit | F12: Balance Sheet
B13: 1600 | C13: Intangible Assets | D13: Asset | E13: Debit | F13: Balance Sheet
B14: 1610 | C14: Accumulated Amortization | D14: Contra-Asset | E14: Credit | F14: Balance Sheet
... B46: 6400 | C46: Other Expenses | D46: Expense | E46: Debit | F46: Income Statement
B49: ACCOUNT TYPE COLOR LEGEND
B50: Asset
B51: Liability
B52: Equity
B53: Revenue
B54: Expense
B55: Contra-Asset

Sheet General Journal
B2: =IFERROR("GENERAL JOURNAL — Smart Monthly Ledger | Fiscal Year: "&TEXT(G3,"0"),"GENERAL JOURNAL") -> GENERAL JOURNAL — Smart Monthly Ledger | Fiscal Year: 2025
B3: VIEW MONTH: | D3: All Months | F3: FISCAL YEAR: | G3: 2025 | H3: ← Enter year | Select month → click ▶ FILTER MONTH button | Click SHOW ALL to reset
B4: Blue = input cells | Green = auto-filled | Column D auto-tags month from date | Enter date as YYYY-MM-DD
B5: ★ DOUBLE-ENTRY RULE: Each journal entry must have Total Debits = Total Credits ★
B6: JOURNAL TOTALS (All): | D6: Total Debits: | E6: =IFERROR(SUM(H10:H1809),0) -> 0 | F6: Total Credits: | G6: =IFERROR(SUM(I10:I1809),0) -> 0 | H6: =IF(E6=G6,"✔ BALANCED","✖ OUT OF BALANCE") -> ✔ BALANCED | I6: ← Check this before generating Financial Statements
B9: # | C9: Date | D9: Month | E9: Acct # | F9: Account Name | G9: Ref / Memo | H9: Debit (₱) | I9: Credit (₱) | J9: Entry Type
B10: =IF(C10="","",ROW()-9) | D10: =IF(C10="","",IFERROR(TEXT(C10,"MMMM"),"")) | F10: =IF(E10="","",IFERROR(INDEX('Chart of Accounts'!$C$4:$C$200,MATCH(TEXT(E10,"@"),TEXT('Chart of Accounts'!$B$4:$B$200,"@"),0)),"⚠ Not Found"))
B11: =IF(C11="","",ROW()-9) | D11: =IF(C11="","",IFERROR(TEXT(C11,"MMMM"),"")) | F11: =IF(E11="","",IFERROR(INDEX('Chart of Accounts'!$C$4:$C$200,MATCH(TEXT(E11,"@"),TEXT('Chart of Accounts'!$B$4:$B$200,"@"),0)),"⚠ Not Found"))
B12: =IF(C12="","",ROW()-9) | D12: =IF(C12="","",IFERROR(TEXT(C12,"MMMM"),"")) | F12: =IF(E12="","",IFERROR(INDEX('Chart of Accounts'!$C$4:$C$200,MATCH(TEXT(E12,"@"),TEXT('Chart of Accounts'!$B$4:$B$200,"@"),0)),"⚠ Not Found"))
B13: =IF(C13="","",ROW()-9) | D13: =IF(C13="","",IFERROR(TEXT(C13,"MMMM"),"")) | F13: =IF(E13="","",IFERROR(INDEX('Chart of Accounts'!$C$4:$C$200,MATCH(TEXT(E13,"@"),TEXT('Chart of Accounts'!$B$4:$B$200,"@"),0)),"⚠ Not Found"))
B14: =IF(C14="","",ROW()-9) | D14: =IF(C14="","",IFERROR(TEXT(C14,"MMMM"),"")) | F14: =IF(E14="","",IFERROR(INDEX('Chart of Accounts'!$C$4:$C$200,MATCH(TEXT(E14,"@"),TEXT('Chart of Accounts'!$B$4:$B$200,"@"),0)),"⚠ Not Found"))
B15: =IF(C15="","",ROW()-9) | D15: =IF(C15="","",IFERROR(TEXT(C15,"MMMM"),"")) | F15: =IF(E15="","",IFERROR(INDEX('Chart of Accounts'!$C$4:$C$200,MATCH(TEXT(E15,"@"),TEXT('Chart of Accounts'!$B$4:$B$200,"@"),0)),"⚠ Not Found"))
B16: =IF(C16="","",ROW()-9) | D16: =IF(C16="","",IFERROR(TEXT(C16,"MMMM"),"")) | F16: =IF(E16="","",IFERROR(INDEX('Chart of Accounts'!$C$4:$C$200,MATCH(TEXT(E16,"@"),TEXT('Chart of Accounts'!$B$4:$B$200,"@"),0)),"⚠ Not Found"))
B17: =IF(C17="","",ROW()-9) | D17: =IF(C17="","",IFERROR(TEXT(C17,"MMMM"),"")) | F17: =IF(E17="","",IFERROR(INDEX('Chart of Accounts'!$C$4:$C$200,MATCH(TEXT(E17,"@"),TEXT('Chart of Accounts'!$B$4:$B$200,"@"),0)),"⚠ Not Found"))
B18: =IF(C18="","",ROW()-9) | D18: =IF(C18="","",IFERROR(TEXT(C18,"MMMM"),"")) | F18: =IF(E18="","",IFERROR(INDEX('Chart of Accounts'!$C$4:$C$200,MATCH(TEXT(E18,"@"),TEXT('Chart of Accounts'!$B$4:$B$200,"@"),0)),"⚠ Not Found"))
B19: =IF(C19="","",ROW()-9) | D19: =IF(C19="","",IFERROR(TEXT(C19,"MMMM"),"")) | F19: =IF(E19="","",IFERROR(INDEX('Chart of Accounts'!$C$4:$C$200,MATCH(TEXT(E19,"@"),TEXT('Chart of Accounts'!$B$4:$B$200,"@"),0)),"⚠ Not Found"))
B20: =IF(C20="","",ROW()-9) | D20: =IF(C20="","",IFERROR(TEXT(C20,"MMMM"),"")) | F20: =IF(E20="","",IFERROR(INDEX('Chart of Accounts'!$C$4:$C$200,MATCH(TEXT(E20,"@"),TEXT('Chart of Accounts'!$B$4:$B$200,"@"),0)),"⚠ Not Found"))
B21: =IF(C21="","",ROW()-9) | D21: =IF(C21="","",IFERROR(TEXT(C21,"MMMM"),"")) | F21: =IF(E21="","",IFERROR(INDEX('Chart of Accounts'!$C$4:$C$200,MATCH(TEXT(E21,"@"),TEXT('Chart of Accounts'!$B$4:$B$200,"@"),0)),"⚠ Not Found"))
... B1809: =IF(C1809="","",ROW()-9) | D1809: =IF(C1809="","",IFERROR(TEXT(C1809,"MMMM"),"")) | F1809: =IF(E1809="","",IFERROR(INDEX('Chart of Accounts'!$C$4:$C$200,MATCH(TEXT(E1809,"@"),TEXT('Chart of Accounts'!$B$4:$B$200,"@"),0)),"⚠ Not Found"))

Sheet General Ledger & Trial Balance
B2: =IFERROR("GENERAL LEDGER & TRIAL BALANCE | Fiscal Year: "&TEXT(H3,"0"),"GENERAL LEDGER & TRIAL BALANCE") -> GENERAL LEDGER & TRIAL BALANCE | Fiscal Year: ← Type the year here
B3: PERIOD TYPE: | D3: Monthly | F3: FISCAL YEAR: | G3: 2025 | H3: ← Type the year here
B4: PERIOD VALUE: | D4: January
B5: PERIOD LABEL: | D5: =IF(D3="Annually","Full Year "&TEXT(H3,"0"),IF(D3="Cumulative As Of","As of "&D4&" "&TEXT(H3,"0"),IF(D3="Quarterly",D4&" "&TEXT(H3,"0"),D4&" "&TEXT(H3,"0")))) -> January ← Type the year here
B6: [Start Month #] | D6: =IF(D3="Annually",1,IF(D3="Cumulative As Of",IFERROR(MATCH(D4,{"January","February","March","April","May","June","July","August","September","October","November","December"},0),1),IF(D3="Quarterly",IF(D4="Q1 (Jan-Mar)",1,IF(D4="Q2 (Apr-Jun)",4,IF(D4="Q3 (Jul-Sep)",7,10))),IFERROR(MATCH(D4,{"January","February","March","April","May","June","July","August","September","October","November","December"},0),1)))) -> 1 | E6: [End Month #] | G6: =IF(D3="Annually",12,IF(D3="Cumulative As Of",IFERROR(MATCH(D4,{"January","February","March","April","May","June","July","August","September","October","November","December"},0),12),IF(D3="Quarterly",IF(D4="Q1 (Jan-Mar)",3,IF(D4="Q2 (Apr-Jun)",6,IF(D4="Q3 (Jul-Sep)",9,12))),IFERROR(MATCH(D4,{"January","February","March","April","May","June","July","August","September","October","November","December"},0),1)))) -> 1 | H6: =G6 -> 1
B8: ▶ Set Period Type (D3) and Period Value (D4) above, then click the MACRO BUTTON to generate Financial Statements
B9: ℹ Balance Sheet is always Cumulative as of period end | Income Tax Expense (Acct 6200) = manual journal entry only — compute tax per BIR rules
B11: Acct # | C11: Account Name | D11: Account Type | E11: Normal Balance | F11: Total Debits (₱) | G11: Total Credits (₱) | H11: Net Balance (₱)
B12: 1000 | C12: Cash and Cash Equivalents | D12: Asset | E12: Debit | F12: =IFERROR(SUMPRODUCT((TEXT('General Journal'!$E$10:$E$1809,"@")=TEXT("1000","@"))*(MONTH('General Journal'!$C$10:$C$1809)>=$D$6)*(MONTH('General Journal'!$C$10:$C$1809)<=$H$6)*(ISNUMBER('General Journal'!$C$10:$C$1809))*'General Journal'!$H$10:$H$1809),0) -> 0 | G12: =IFERROR(SUMPRODUCT((TEXT('General Journal'!$E$10:$E$1809,"@")=TEXT("1000","@"))*(MONTH('General Journal'!$C$10:$C$1809)>=$D$6)*(MONTH('General Journal'!$C$10:$C$1809)<=$H$6)*(ISNUMBER('General Journal'!$C$10:$C$1809))*'General Journal'!$I$10:$I$1809),0) -> 0 | H12: =F12-G12 -> 0
B13: 1010 | C13: Petty Cash | D13: Asset | E13: Debit | F13: =IFERROR(SUMPRODUCT((TEXT('General Journal'!$E$10:$E$1809,"@")=TEXT("1010","@"))*(MONTH('General Journal'!$C$10:$C$1809)>=$D$6)*(MONTH('General Journal'!$C$10:$C$1809)<=$H$6)*(ISNUMBER('General Journal'!$C$10:$C$1809))*'General Journal'!$H$10:$H$1809),0) -> 0 | G13: =IFERROR(SUMPRODUCT((TEXT('General Journal'!$E$10:$E$1809,"@")=TEXT("1010","@"))*(MONTH('General Journal'!$C$10:$C$1809)>=$D$6)*(MONTH('General Journal'!$C$10:$C$1809)<=$H$6)*(ISNUMBER('General Journal'!$C$10:$C$1809))*'General Journal'!$I$10:$I$1809),0) -> 0 | H13: =F13-G13 -> 0
B14: 1100 | C14: Accounts Receivable | D14: Asset | E14: Debit | F14: =IFERROR(SUMPRODUCT((TEXT('General Journal'!$E$10:$E$1809,"@")=TEXT("1100","@"))*(MONTH('General Journal'!$C$10:$C$1809)>=$D$6)*(MONTH('General Journal'!$C$10:$C$1809)<=$H$6)*(ISNUMBER('General Journal'!$C$10:$C$1809))*'General Journal'!$H$10:$H$1809),0) -> 0 | G14: =IFERROR(SUMPRODUCT((TEXT('General Journal'!$E$10:$E$1809,"@")=TEXT("1100","@"))*(MONTH('General Journal'!$C$10:$C$1809)>=$D$6)*(MONTH('General Journal'!$C$10:$C$1809)<=$H$6)*(ISNUMBER('General Journal'!$C$10:$C$1809))*'General Journal'!$I$10:$I$1809),0) -> 0 | H14: =F14-G14 -> 0
B15: 1110 | C15: Allowance for Doubtful Accounts | D15: Contra-Asset | E15: Credit | F15: =IFERROR(SUMPRODUCT((TEXT('General Journal'!$E$10:$E$1809,"@")=TEXT("1110","@"))*(MONTH('General Journal'!$C$10:$C$1809)>=$D$6)*(MONTH('General Journal'!$C$10:$C$1809)<=$H$6)*(ISNUMBER('General Journal'!$C$10:$C$1809))*'General Journal'!$H$10:$H$1809),0) -> 0 | G15: =IFERROR(SUMPRODUCT((TEXT('General Journal'!$E$10:$E$1809,"@")=TEXT("1110","@"))*(MONTH('General Journal'!$C$10:$C$1809)>=$D$6)*(MONTH('General Journal'!$C$10:$C$1809)<=$H$6)*(ISNUMBER('General Journal'!$C$10:$C$1809))*'General Journal'!$I$10:$I$1809),0) -> 0 | H15: =G15-F15 -> 0
B16: 1200 | C16: Inventory | D16: Asset | E16: Debit | F16: =IFERROR(SUMPRODUCT((TEXT('General Journal'!$E$10:$E$1809,"@")=TEXT("1200","@"))*(MONTH('General Journal'!$C$10:$C$1809)>=$D$6)*(MONTH('General Journal'!$C$10:$C$1809)<=$H$6)*(ISNUMBER('General Journal'!$C$10:$C$1809))*'General Journal'!$H$10:$H$1809),0) -> 0 | G16: =IFERROR(SUMPRODUCT((TEXT('General Journal'!$E$10:$E$1809,"@")=TEXT("1200","@"))*(MONTH('General Journal'!$C$10:$C$1809)>=$D$6)*(MONTH('General Journal'!$C$10:$C$1809)<=$H$6)*(ISNUMBER('General Journal'!$C$10:$C$1809))*'General Journal'!$I$10:$I$1809),0) -> 0 | H16: =F16-G16 -> 0
B17: 1300 | C17: Prepaid Expenses | D17: Asset | E17: Debit | F17: =IFERROR(SUMPRODUCT((TEXT('General Journal'!$E$10:$E$1809,"@")=TEXT("1300","@"))*(MONTH('General Journal'!$C$10:$C$1809)>=$D$6)*(MONTH('General Journal'!$C$10:$C$1809)<=$H$6)*(ISNUMBER('General Journal'!$C$10:$C$1809))*'General Journal'!$H$10:$H$1809),0) -> 0 | G17: =IFERROR(SUMPRODUCT((TEXT('General Journal'!$E$10:$E$1809,"@")=TEXT("1300","@"))*(MONTH('General Journal'!$C$10:$C$1809)>=$D$6)*(MONTH('General Journal'!$C$10:$C$1809)<=$H$6)*(ISNUMBER('General Journal'!$C$10:$C$1809))*'General Journal'!$I$10:$I$1809),0) -> 0 | H17: =F17-G17 -> 0
B18: 1400 | C18: Short-term Investments | D18: Asset | E18: Debit | F18: =IFERROR(SUMPRODUCT((TEXT('General Journal'!$E$10:$E$1809,"@")=TEXT("1400","@"))*(MONTH('General Journal'!$C$10:$C$1809)>=$D$6)*(MONTH('General Journal'!$C$10:$C$1809)<=$H$6)*(ISNUMBER('General Journal'!$C$10:$C$1809))*'General Journal'!$H$10:$H$1809),0) -> 0 | G18: =IFERROR(SUMPRODUCT((TEXT('General Journal'!$E$10:$E$1809,"@")=TEXT("1400","@"))*(MONTH('General Journal'!$C$10:$C$1809)>=$D$6)*(MONTH('General Journal'!$C$10:$C$1809)<=$H$6)*(ISNUMBER('General Journal'!$C$10:$C$1809))*'General Journal'!$I$10:$I$1809),0) -> 0 | H18: =F18-G18 -> 0
B19: 1500 | C19: Property, Plant & Equipment | D19: Asset | E19: Debit | F19: =IFERROR(SUMPRODUCT((TEXT('General Journal'!$E$10:$E$1809,"@")=TEXT("1500","@"))*(MONTH('General Journal'!$C$10:$C$1809)>=$D$6)*(MONTH('General Journal'!$C$10:$C$1809)<=$H$6)*(ISNUMBER('General Journal'!$C$10:$C$1809))*'General Journal'!$H$10:$H$1809),0) -> 0 | G19: =IFERROR(SUMPRODUCT((TEXT('General Journal'!$E$10:$E$1809,"@")=TEXT("1500","@"))*(MONTH('General Journal'!$C$10:$C$1809)>=$D$6)*(MONTH('General Journal'!$C$10:$C$1809)<=$H$6)*(ISNUMBER('General Journal'!$C$10:$C$1809))*'General Journal'!$I$10:$I$1809),0) -> 0 | H19: =F19-G19 -> 0
B20: 1510 | C20: Accumulated Depreciation | D20: Contra-Asset | E20: Credit | F20: =IFERROR(SUMPRODUCT((TEXT('General Journal'!$E$10:$E$1809,"@")=TEXT("1510","@"))*(MONTH('General Journal'!$C$10:$C$1809)>=$D$6)*(MONTH('General Journal'!$C$10:$C$1809)<=$H$6)*(ISNUMBER('General Journal'!$C$10:$C$1809))*'General Journal'!$H$10:$H$1809),0) -> 0 | G20: =IFERROR(SUMPRODUCT((TEXT('General Journal'!$E$10:$E$1809,"@")=TEXT("1510","@"))*(MONTH('General Journal'!$C$10:$C$1809)>=$D$6)*(MONTH('General Journal'!$C$10:$C$1809)<=$H$6)*(ISNUMBER('General Journal'!$C$10:$C$1809))*'General Journal'!$I$10:$I$1809),0) -> 0 | H20: =G20-F20 -> 0
B21: 1600 | C21: Intangible Assets | D21: Asset | E21: Debit | F21: =IFERROR(SUMPRODUCT((TEXT('General Journal'!$E$10:$E$1809,"@")=TEXT("1600","@"))*(MONTH('General Journal'!$C$10:$C$1809)>=$D$6)*(MONTH('General Journal'!$C$10:$C$1809)<=$H$6)*(ISNUMBER('General Journal'!$C$10:$C$1809))*'General Journal'!$H$10:$H$1809),0) -> 0 | G21: =IFERROR(SUMPRODUCT((TEXT('General Journal'!$E$10:$E$1809,"@")=TEXT("1600","@"))*(MONTH('General Journal'!$C$10:$C$1809)>=$D$6)*(MONTH('General Journal'!$C$10:$C$1809)<=$H$6)*(ISNUMBER('General Journal'!$C$10:$C$1809))*'General Journal'!$I$10:$I$1809),0) -> 0 | H21: =F21-G21 -> 0
B22: 1610 | C22: Accumulated Amortization | D22: Contra-Asset | E22: Credit | F22: =IFERROR(SUMPRODUCT((TEXT('General Journal'!$E$10:$E$1809,"@")=TEXT("1610","@"))*(MONTH('General Journal'!$C$10:$C$1809)>=$D$6)*(MONTH('General Journal'!$C$10:$C$1809)<=$H$6)*(ISNUMBER('General Journal'!$C$10:$C$1809))*'General Journal'!$H$10:$H$1809),0) -> 0 | G22: =IFERROR(SUMPRODUCT((TEXT('General Journal'!$E$10:$E$1809,"@")=TEXT("1610","@"))*(MONTH('General Journal'!$C$10:$C$1809)>=$D$6)*(MONTH('General Journal'!$C$10:$C$1809)<=$H$6)*(ISNUMBER('General Journal'!$C$10:$C$1809))*'General Journal'!$I$10:$I$1809),0) -> 0 | H22: =G22-F22 -> 0
B23: 1700 | C23: Other Long-term Assets | D23: Asset | E23: Debit | F23: =IFERROR(SUMPRODUCT((TEXT('General Journal'!$E$10:$E$1809,"@")=TEXT("1700","@"))*(MONTH('General Journal'!$C$10:$C$1809)>=$D$6)*(MONTH('General Journal'!$C$10:$C$1809)<=$H$6)*(ISNUMBER('General Journal'!$C$10:$C$1809))*'General Journal'!$H$10:$H$1809),0) -> 0 | G23: =IFERROR(SUMPRODUCT((TEXT('General Journal'!$E$10:$E$1809,"@")=TEXT("1700","@"))*(MONTH('General Journal'!$C$10:$C$1809)>=$D$6)*(MONTH('General Journal'!$C$10:$C$1809)<=$H$6)*(ISNUMBER('General Journal'!$C$10:$C$1809))*'General Journal'!$I$10:$I$1809),0) -> 0 | H23: =F23-G23 -> 0
B24: 2000 | C24: Accounts Payable | D24: Liability | E24: Credit | F24: =IFERROR(SUMPRODUCT((TEXT('General Journal'!$E$10:$E$1809,"@")=TEXT("2000","@"))*(MONTH('General Journal'!$C$10:$C$1809)>=$D$6)*(MONTH('General Journal'!$C$10:$C$1809)<=$H$6)*(ISNUMBER('General Journal'!$C$10:$C$1809))*'General Journal'!$H$10:$H$1809),0) -> 0 | G24: =IFERROR(SUMPRODUCT((TEXT('General Journal'!$E$10:$E$1809,"@")=TEXT("2000","@"))*(MONTH('General Journal'!$C$10:$C$1809)>=$D$6)*(MONTH('General Journal'!$C$10:$C$1809)<=$H$6)*(ISNUMBER('General Journal'!$C$10:$C$1809))*'General Journal'!$I$10:$I$1809),0) -> 0 | H24: =G24-F24 -> 0
B25: 2100 | C25: Accrued Liabilities | D25: Liability | E25: Credit | F25: =IFERROR(SUMPRODUCT((TEXT('General Journal'!$E$10:$E$1809,"@")=TEXT("2100","@"))*(MONTH('General Journal'!$C$10:$C$1809)>=$D$6)*(MONTH('General Journal'!$C$10:$C$1809)<=$H$6)*(ISNUMBER('General Journal'!$C$10:$C$1809))*'General Journal'!$H$10:$H$1809),0) -> 0 | G25: =IFERROR(SUMPRODUCT((TEXT('General Journal'!$E$10:$E$1809,"@")=TEXT("2100","@"))*(MONTH('General Journal'!$C$10:$C$1809)>=$D$6)*(MONTH('General Journal'!$C$10:$C$1809)<=$H$6)*(ISNUMBER('General Journal'!$C$10:$C$1809))*'General Journal'!$I$10:$I$1809),0) -> 0 | H25: =G25-F25 -> 0
B26: 2200 | C26: Salaries Payable | D26: Liability | E26: Credit | F26: =IFERROR(SUMPRODUCT((TEXT('General Journal'!$E$10:$E$1809,"@")=TEXT("2200","@"))*(MONTH('General Journal'!$C$10:$C$1809)>=$D$6)*(MONTH('General Journal'!$C$10:$C$1809)<=$H$6)*(ISNUMBER('General Journal'!$C$10:$C$1809))*'General Journal'!$H$10:$H$1809),0) -> 0 | G26: =IFERROR(SUMPRODUCT((TEXT('General Journal'!$E$10:$E$1809,"@")=TEXT("2200","@"))*(MONTH('General Journal'!$C$10:$C$1809)>=$D$6)*(MONTH('General Journal'!$C$10:$C$1809)<=$H$6)*(ISNUMBER('General Journal'!$C$10:$C$1809))*'General Journal'!$I$10:$I$1809),0) -> 0 | H26: =G26-F26 -> 0
B27: 2300 | C27: Taxes Payable | D27: Liability | E27: Credit | F27: =IFERROR(SUMPRODUCT((TEXT('General Journal'!$E$10:$E$1809,"@")=TEXT("2300","@"))*(MONTH('General Journal'!$C$10:$C$1809)>=$D$6)*(MONTH('General Journal'!$C$10:$C$1809)<=$H$6)*(ISNUMBER('General Journal'!$C$10:$C$1809))*'General Journal'!$H$10:$H$1809),0) -> 0 | G27: =IFERROR(SUMPRODUCT((TEXT('General Journal'!$E$10:$E$1809,"@")=TEXT("2300","@"))*(MONTH('General Journal'!$C$10:$C$1809)>=$D$6)*(MONTH('General Journal'!$C$10:$C$1809)<=$H$6)*(ISNUMBER('General Journal'!$C$10:$C$1809))*'General Journal'!$I$10:$I$1809),0) -> 0 | H27: =G27-F27 -> 0
B28: 2400 | C28: Unearned Revenue | D28: Liability | E28: Credit | F28: =IFERROR(SUMPRODUCT((TEXT('General Journal'!$E$10:$E$1809,"@")=TEXT("2400","@"))*(MONTH('General Journal'!$C$10:$C$1809)>=$D$6)*(MONTH('General Journal'!$C$10:$C$1809)<=$H$6)*(ISNUMBER('General Journal'!$C$10:$C$1809))*'General Journal'!$H$10:$H$1809),0) -> 0 | G28: =IFERROR(SUMPRODUCT((TEXT('General Journal'!$E$10:$E$1809,"@")=TEXT("2400","@"))*(MONTH('General Journal'!$C$10:$C$1809)>=$D$6)*(MONTH('General Journal'!$C$10:$C$1809)<=$H$6)*(ISNUMBER('General Journal'!$C$10:$C$1809))*'General Journal'!$I$10:$I$1809),0) -> 0 | H28: =G28-F28 -> 0
B29: 2500 | C29: Notes Payable - Current | D29: Liability | E29: Credit | F29: =IFERROR(SUMPRODUCT((TEXT('General Journal'!$E$10:$E$1809,"@")=TEXT("2500","@"))*(MONTH('General Journal'!$C$10:$C$1809)>=$D$6)*(MONTH('General Journal'!$C$10:$C$1809)<=$H$6)*(ISNUMBER('General Journal'!$C$10:$C$1809))*'General Journal'!$H$10:$H$1809),0) -> 0 | G29: =IFERROR(SUMPRODUCT((TEXT('General Journal'!$E$10:$E$1809,"@")=TEXT("2500","@"))*(MONTH('General Journal'!$C$10:$C$1809)>=$D$6)*(MONTH('General Journal'!$C$10:$C$1809)<=$H$6)*(ISNUMBER('General Journal'!$C$10:$C$1809))*'General Journal'!$I$10:$I$1809),0) -> 0 | H29: =G29-F29 -> 0
B30: 2600 | C30: Long-term Debt | D30: Liability | E30: Credit | F30: =IFERROR(SUMPRODUCT((TEXT('General Journal'!$E$10:$E$1809,"@")=TEXT("2600","@"))*(MONTH('General Journal'!$C$10:$C$1809)>=$D$6)*(MONTH('General Journal'!$C$10:$C$1809)<=$H$6)*(ISNUMBER('General Journal'!$C$10:$C$1809))*'General Journal'!$H$10:$H$1809),0) -> 0 | G30: =IFERROR(SUMPRODUCT((TEXT('General Journal'!$E$10:$E$1809,"@")=TEXT("2600","@"))*(MONTH('General Journal'!$C$10:$C$1809)>=$D$6)*(MONTH('General Journal'!$C$10:$C$1809)<=$H$6)*(ISNUMBER('General Journal'!$C$10:$C$1809))*'General Journal'!$I$10:$I$1809),0) -> 0 | H30: =G30-F30 -> 0
B31: 2700 | C31: Deferred Tax Liability | D31: Liability | E31: Credit | F31: =IFERROR(SUMPRODUCT((TEXT('General Journal'!$E$10:$E$1809,"@")=TEXT("2700","@"))*(MONTH('General Journal'!$C$10:$C$1809)>=$D$6)*(MONTH('General Journal'!$C$10:$C$1809)<=$H$6)*(ISNUMBER('General Journal'!$C$10:$C$1809))*'General Journal'!$H$10:$H$1809),0) -> 0 | G31: =IFERROR(SUMPRODUCT((TEXT('General Journal'!$E$10:$E$1809,"@")=TEXT("2700","@"))*(MONTH('General Journal'!$C$10:$C$1809)>=$D$6)*(MONTH('General Journal'!$C$10:$C$1809)<=$H$6)*(ISNUMBER('General Journal'!$C$10:$C$1809))*'General Journal'!$I$10:$I$1809),0) -> 0 | H31: =G31-F31 -> 0
B32: 3000 | C32: Owner's Capital / Common Stock | D32: Equity | E32: Credit | F32: =IFERROR(SUMPRODUCT((TEXT('General Journal'!$E$10:$E$1809,"@")=TEXT("3000","@"))*(MONTH('General Journal'!$C$10:$C$1809)>=$D$6)*(MONTH('General Journal'!$C$10:$C$1809)<=$H$6)*(ISNUMBER('General Journal'!$C$10:$C$1809))*'General Journal'!$H$10:$H$1809),0) -> 0 | G32: =IFERROR(SUMPRODUCT((TEXT('General Journal'!$E$10:$E$1809,"@")=TEXT("3000","@"))*(MONTH('General Journal'!$C$10:$C$1809)>=$D$6)*(MONTH('General Journal'!$C$10:$C$1809)<=$H$6)*(ISNUMBER('General Journal'!$C$10:$C$1809))*'General Journal'!$I$10:$I$1809),0) -> 0 | H32: =G32-F32 -> 0
B33: 3100 | C33: Retained Earnings | D33: Equity | E33: Credit | F33: =IFERROR(SUMPRODUCT((TEXT('General Journal'!$E$10:$E$1809,"@")=TEXT("3100","@"))*(MONTH('General Journal'!$C$10:$C$1809)>=$D$6)*(MONTH('General Journal'!$C$10:$C$1809)<=$H$6)*(ISNUMBER('General Journal'!$C$10:$C$1809))*'General Journal'!$H$10:$H$1809),0) -> 0 | G33: =IFERROR(SUMPRODUCT((TEXT('General Journal'!$E$10:$E$1809,"@")=TEXT("3100","@"))*(MONTH('General Journal'!$C$10:$C$1809)>=$D$6)*(MONTH('General Journal'!$C$10:$C$1809)<=$H$6)*(ISNUMBER('General Journal'!$C$10:$C$1809))*'General Journal'!$I$10:$I$1809),0) -> 0 | H33: =G33-F33 -> 0
B34: 3200 | C34: Additional Paid-in Capital | D34: Equity | E34: Credit | F34: =IFERROR(SUMPRODUCT((TEXT('General Journal'!$E$10:$E$1809,"@")=TEXT("3200","@"))*(MONTH('General Journal'!$C$10:$C$1809)>=$D$6)*(MONTH('General Journal'!$C$10:$C$1809)<=$H$6)*(ISNUMBER('General Journal'!$C$10:$C$1809))*'General Journal'!$H$10:$H$1809),0) -> 0 | G34: =IFERROR(SUMPRODUCT((TEXT('General Journal'!$E$10:$E$1809,"@")=TEXT("3200","@"))*(MONTH('General Journal'!$C$10:$C$1809)>=$D$6)*(MONTH('General Journal'!$C$10:$C$1809)<=$H$6)*(ISNUMBER('General Journal'!$C$10:$C$1809))*'General Journal'!$I$10:$I$1809),0) -> 0 | H34: =G34-F34 -> 0
B35: 3300 | C35: Owner's Drawings / Dividends | D35: Equity | E35: Debit | F35: =IFERROR(SUMPRODUCT((TEXT('General Journal'!$E$10:$E$1809,"@")=TEXT("3300","@"))*(MONTH('General Journal'!$C$10:$C$1809)>=$D$6)*(MONTH('General Journal'!$C$10:$C$1809)<=$H$6)*(ISNUMBER('General Journal'!$C$10:$C$1809))*'General Journal'!$H$10:$H$1809),0) -> 0 | G35: =IFERROR(SUMPRODUCT((TEXT('General Journal'!$E$10:$E$1809,"@")=TEXT("3300","@"))*(MONTH('General Journal'!$C$10:$C$1809)>=$D$6)*(MONTH('General Journal'!$C$10:$C$1809)<=$H$6)*(ISNUMBER('General Journal'!$C$10:$C$1809))*'General Journal'!$I$10:$I$1809),0) -> 0 | H35: =F35-G35 -> 0
B36: 4000 | C36: Sales Revenue | D36: Revenue | E36: Credit | F36: =IFERROR(SUMPRODUCT((TEXT('General Journal'!$E$10:$E$1809,"@")=TEXT("4000","@"))*(MONTH('General Journal'!$C$10:$C$1809)>=$D$6)*(MONTH('General Journal'!$C$10:$C$1809)<=$H$6)*(ISNUMBER('General Journal'!$C$10:$C$1809))*'General Journal'!$H$10:$H$1809),0) -> 0 | G36: =IFERROR(SUMPRODUCT((TEXT('General Journal'!$E$10:$E$1809,"@")=TEXT("4000","@"))*(MONTH('General Journal'!$C$10:$C$1809)>=$D$6)*(MONTH('General Journal'!$C$10:$C$1809)<=$H$6)*(ISNUMBER('General Journal'!$C$10:$C$1809))*'General Journal'!$I$10:$I$1809),0) -> 0 | H36: =G36-F36 -> 0
B37: 4100 | C37: Service Revenue | D37: Revenue | E37: Credit | F37: =IFERROR(SUMPRODUCT((TEXT('General Journal'!$E$10:$E$1809,"@")=TEXT("4100","@"))*(MONTH('General Journal'!$C$10:$C$1809)>=$D$6)*(MONTH('General Journal'!$C$10:$C$1809)<=$H$6)*(ISNUMBER('General Journal'!$C$10:$C$1809))*'General Journal'!$H$10:$H$1809),0) -> 0 | G37: =IFERROR(SUMPRODUCT((TEXT('General Journal'!$E$10:$E$1809,"@")=TEXT("4100","@"))*(MONTH('General Journal'!$C$10:$C$1809)>=$D$6)*(MONTH('General Journal'!$C$10:$C$1809)<=$H$6)*(ISNUMBER('General Journal'!$C$10:$C$1809))*'General Journal'!$I$10:$I$1809),0) -> 0 | H37: =G37-F37 -> 0
B38: 4200 | C38: Interest Income | D38: Revenue | E38: Credit | F38: =IFERROR(SUMPRODUCT((TEXT('General Journal'!$E$10:$E$1809,"@")=TEXT("4200","@"))*(MONTH('General Journal'!$C$10:$C$1809)>=$D$6)*(MONTH('General Journal'!$C$10:$C$1809)<=$H$6)*(ISNUMBER('General Journal'!$C$10:$C$1809))*'General Journal'!$H$10:$H$1809),0) -> 0 | G38: =IFERROR(SUMPRODUCT((TEXT('General Journal'!$E$10:$E$1809,"@")=TEXT("4200","@"))*(MONTH('General Journal'!$C$10:$C$1809)>=$D$6)*(MONTH('General Journal'!$C$10:$C$1809)<=$H$6)*(ISNUMBER('General Journal'!$C$10:$C$1809))*'General Journal'!$I$10:$I$1809),0) -> 0 | H38: =G38-F38 -> 0
B39: 4300 | C39: Other Income | D39: Revenue | E39: Credit | F39: =IFERROR(SUMPRODUCT((TEXT('General Journal'!$E$10:$E$1809,"@")=TEXT("4300","@"))*(MONTH('General Journal'!$C$10:$C$1809)>=$D$6)*(MONTH('General Journal'!$C$10:$C$1809)<=$H$6)*(ISNUMBER('General Journal'!$C$10:$C$1809))*'General Journal'!$H$10:$H$1809),0) -> 0 | G39: =IFERROR(SUMPRODUCT((TEXT('General Journal'!$E$10:$E$1809,"@")=TEXT("4300","@"))*(MONTH('General Journal'!$C$10:$C$1809)>=$D$6)*(MONTH('General Journal'!$C$10:$C$1809)<=$H$6)*(ISNUMBER('General Journal'!$C$10:$C$1809))*'General Journal'!$I$10:$I$1809),0) -> 0 | H39: =G39-F39 -> 0
B40: 5000 | C40: Cost of Goods Sold | D40: Expense | E40: Debit | F40: =IFERROR(SUMPRODUCT((TEXT('General Journal'!$E$10:$E$1809,"@")=TEXT("5000","@"))*(MONTH('General Journal'!$C$10:$C$1809)>=$D$6)*(MONTH('General Journal'!$C$10:$C$1809)<=$H$6)*(ISNUMBER('General Journal'!$C$10:$C$1809))*'General Journal'!$H$10:$H$1809),0) -> 0 | G40: =IFERROR(SUMPRODUCT((TEXT('General Journal'!$E$10:$E$1809,"@")=TEXT("5000","@"))*(MONTH('General Journal'!$C$10:$C$1809)>=$D$6)*(MONTH('General Journal'!$C$10:$C$1809)<=$H$6)*(ISNUMBER('General Journal'!$C$10:$C$1809))*'General Journal'!$I$10:$I$1809),0) -> 0 | H40: =F40-G40 -> 0
B41: 5100 | C41: Advertising & Marketing Expense | D41: Expense | E41: Debit | F41: =IFERROR(SUMPRODUCT((TEXT('General Journal'!$E$10:$E$1809,"@")=TEXT("5100","@"))*(MONTH('General Journal'!$C$10:$C$1809)>=$D$6)*(MONTH('General Journal'!$C$10:$C$1809)<=$H$6)*(ISNUMBER('General Journal'!$C$10:$C$1809))*'General Journal'!$H$10:$H$1809),0) -> 0 | G41: =IFERROR(SUMPRODUCT((TEXT('General Journal'!$E$10:$E$1809,"@")=TEXT("5100","@"))*(MONTH('General Journal'!$C$10:$C$1809)>=$D$6)*(MONTH('General Journal'!$C$10:$C$1809)<=$H$6)*(ISNUMBER('General Journal'!$C$10:$C$1809))*'General Journal'!$I$10:$I$1809),0) -> 0 | H41: =F41-G41 -> 0
B42: 5200 | C42: Bank Charges & Fees | D42: Expense | E42: Debit | F42: =IFERROR(SUMPRODUCT((TEXT('General Journal'!$E$10:$E$1809,"@")=TEXT("5200","@"))*(MONTH('General Journal'!$C$10:$C$1809)>=$D$6)*(MONTH('General Journal'!$C$10:$C$1809)<=$H$6)*(ISNUMBER('General Journal'!$C$10:$C$1809))*'General Journal'!$H$10:$H$1809),0) -> 0 | G42: =IFERROR(SUMPRODUCT((TEXT('General Journal'!$E$10:$E$1809,"@")=TEXT("5200","@"))*(MONTH('General Journal'!$C$10:$C$1809)>=$D$6)*(MONTH('General Journal'!$C$10:$C$1809)<=$H$6)*(ISNUMBER('General Journal'!$C$10:$C$1809))*'General Journal'!$I$10:$I$1809),0) -> 0 | H42: =F42-G42 -> 0
B43: 5300 | C43: Depreciation Expense | D43: Expense | E43: Debit | F43: =IFERROR(SUMPRODUCT((TEXT('General Journal'!$E$10:$E$1809,"@")=TEXT("5300","@"))*(MONTH('General Journal'!$C$10:$C$1809)>=$D$6)*(MONTH('General Journal'!$C$10:$C$1809)<=$H$6)*(ISNUMBER('General Journal'!$C$10:$C$1809))*'General Journal'!$H$10:$H$1809),0) -> 0 | G43: =IFERROR(SUMPRODUCT((TEXT('General Journal'!$E$10:$E$1809,"@")=TEXT("5300","@"))*(MONTH('General Journal'!$C$10:$C$1809)>=$D$6)*(MONTH('General Journal'!$C$10:$C$1809)<=$H$6)*(ISNUMBER('General Journal'!$C$10:$C$1809))*'General Journal'!$I$10:$I$1809),0) -> 0 | H43: =F43-G43 -> 0
B44: 5400 | C44: Insurance Expense | D44: Expense | E44: Debit | F44: =IFERROR(SUMPRODUCT((TEXT('General Journal'!$E$10:$E$1809,"@")=TEXT("5400","@"))*(MONTH('General Journal'!$C$10:$C$1809)>=$D$6)*(MONTH('General Journal'!$C$10:$C$1809)<=$H$6)*(ISNUMBER('General Journal'!$C$10:$C$1809))*'General Journal'!$H$10:$H$1809),0) -> 0 | G44: =IFERROR(SUMPRODUCT((TEXT('General Journal'!$E$10:$E$1809,"@")=TEXT("5400","@"))*(MONTH('General Journal'!$C$10:$C$1809)>=$D$6)*(MONTH('General Journal'!$C$10:$C$1809)<=$H$6)*(ISNUMBER('General Journal'!$C$10:$C$1809))*'General Journal'!$I$10:$I$1809),0) -> 0 | H44: =F44-G44 -> 0
B45: 5500 | C45: Office Supplies Expense | D45: Expense | E45: Debit | F45: =IFERROR(SUMPRODUCT((TEXT('General Journal'!$E$10:$E$1809,"@")=TEXT("5500","@"))*(MONTH('General Journal'!$C$10:$C$1809)>=$D$6)*(MONTH('General Journal'!$C$10:$C$1809)<=$H$6)*(ISNUMBER('General Journal'!$C$10:$C$1809))*'General Journal'!$H$10:$H$1809),0) -> 0 | G45: =IFERROR(SUMPRODUCT((TEXT('General Journal'!$E$10:$E$1809,"@")=TEXT("5500","@"))*(MONTH('General Journal'!$C$10:$C$1809)>=$D$6)*(MONTH('General Journal'!$C$10:$C$1809)<=$H$6)*(ISNUMBER('General Journal'!$C$10:$C$1809))*'General Journal'!$I$10:$I$1809),0) -> 0 | H45: =F45-G45 -> 0
B46: 5600 | C46: Professional Fees Expense | D46: Expense | E46: Debit | F46: =IFERROR(SUMPRODUCT((TEXT('General Journal'!$E$10:$E$1809,"@")=TEXT("5600","@"))*(MONTH('General Journal'!$C$10:$C$1809)>=$D$6)*(MONTH('General Journal'!$C$10:$C$1809)<=$H$6)*(ISNUMBER('General Journal'!$C$10:$C$1809))*'General Journal'!$H$10:$H$1809),0) -> 0 | G46: =IFERROR(SUMPRODUCT((TEXT('General Journal'!$E$10:$E$1809,"@")=TEXT("5600","@"))*(MONTH('General Journal'!$C$10:$C$1809)>=$D$6)*(MONTH('General Journal'!$C$10:$C$1809)<=$H$6)*(ISNUMBER('General Journal'!$C$10:$C$1809))*'General Journal'!$I$10:$I$1809),0) -> 0 | H46: =F46-G46 -> 0
B47: 5700 | C47: Rent Expense | D47: Expense | E47: Debit | F47: =IFERROR(SUMPRODUCT((TEXT('General Journal'!$E$10:$E$1809,"@")=TEXT("5700","@"))*(MONTH('General Journal'!$C$10:$C$1809)>=$D$6)*(MONTH('General Journal'!$C$10:$C$1809)<=$H$6)*(ISNUMBER('General Journal'!$C$10:$C$1809))*'General Journal'!$H$10:$H$1809),0) -> 0 | G47: =IFERROR(SUMPRODUCT((TEXT('General Journal'!$E$10:$E$1809,"@")=TEXT("5700","@"))*(MONTH('General Journal'!$C$10:$C$1809)>=$D$6)*(MONTH('General Journal'!$C$10:$C$1809)<=$H$6)*(ISNUMBER('General Journal'!$C$10:$C$1809))*'General Journal'!$I$10:$I$1809),0) -> 0 | H47: =F47-G47 -> 0
B48: 5800 | C48: Salaries & Wages Expense | D48: Expense | E48: Debit | F48: =IFERROR(SUMPRODUCT((TEXT('General Journal'!$E$10:$E$1809,"@")=TEXT("5800","@"))*(MONTH('General Journal'!$C$10:$C$1809)>=$D$6)*(MONTH('General Journal'!$C$10:$C$1809)<=$H$6)*(ISNUMBER('General Journal'!$C$10:$C$1809))*'General Journal'!$H$10:$H$1809),0) -> 0 | G48: =IFERROR(SUMPRODUCT((TEXT('General Journal'!$E$10:$E$1809,"@")=TEXT("5800","@"))*(MONTH('General Journal'!$C$10:$C$1809)>=$D$6)*(MONTH('General Journal'!$C$10:$C$1809)<=$H$6)*(ISNUMBER('General Journal'!$C$10:$C$1809))*'General Journal'!$I$10:$I$1809),0) -> 0 | H48: =F48-G48 -> 0
B49: 5900 | C49: Taxes & Licenses Expense | D49: Expense | E49: Debit | F49: =IFERROR(SUMPRODUCT((TEXT('General Journal'!$E$10:$E$1809,"@")=TEXT("5900","@"))*(MONTH('General Journal'!$C$10:$C$1809)>=$D$6)*(MONTH('General Journal'!$C$10:$C$1809)<=$H$6)*(ISNUMBER('General Journal'!$C$10:$C$1809))*'General Journal'!$H$10:$H$1809),0) -> 0 | G49: =IFERROR(SUMPRODUCT((TEXT('General Journal'!$E$10:$E$1809,"@")=TEXT("5900","@"))*(MONTH('General Journal'!$C$10:$C$1809)>=$D$6)*(MONTH('General Journal'!$C$10:$C$1809)<=$H$6)*(ISNUMBER('General Journal'!$C$10:$C$1809))*'General Journal'!$I$10:$I$1809),0) -> 0 | H49: =F49-G49 -> 0
B50: 6000 | C50: Travel & Entertainment Expense | D50: Expense | E50: Debit | F50: =IFERROR(SUMPRODUCT((TEXT('General Journal'!$E$10:$E$1809,"@")=TEXT("6000","@"))*(MONTH('General Journal'!$C$10:$C$1809)>=$D$6)*(MONTH('General Journal'!$C$10:$C$1809)<=$H$6)*(ISNUMBER('General Journal'!$C$10:$C$1809))*'General Journal'!$H$10:$H$1809),0) -> 0 | G50: =IFERROR(SUMPRODUCT((TEXT('General Journal'!$E$10:$E$1809,"@")=TEXT("6000","@"))*(MONTH('General Journal'!$C$10:$C$1809)>=$D$6)*(MONTH('General Journal'!$C$10:$C$1809)<=$H$6)*(ISNUMBER('General Journal'!$C$10:$C$1809))*'General Journal'!$I$10:$I$1809),0) -> 0 | H50: =F50-G50 -> 0
B51: 6100 | C51: Utilities Expense | D51: Expense | E51: Debit | F51: =IFERROR(SUMPRODUCT((TEXT('General Journal'!$E$10:$E$1809,"@")=TEXT("6100","@"))*(MONTH('General Journal'!$C$10:$C$1809)>=$D$6)*(MONTH('General Journal'!$C$10:$C$1809)<=$H$6)*(ISNUMBER('General Journal'!$C$10:$C$1809))*'General Journal'!$H$10:$H$1809),0) -> 0 | G51: =IFERROR(SUMPRODUCT((TEXT('General Journal'!$E$10:$E$1809,"@")=TEXT("6100","@"))*(MONTH('General Journal'!$C$10:$C$1809)>=$D$6)*(MONTH('General Journal'!$C$10:$C$1809)<=$H$6)*(ISNUMBER('General Journal'!$C$10:$C$1809))*'General Journal'!$I$10:$I$1809),0) -> 0 | H51: =F51-G51 -> 0
B52: 6200 | C52: Income Tax Expense | D52: Expense | E52: Debit | F52: =IFERROR(SUMPRODUCT((TEXT('General Journal'!$E$10:$E$1809,"@")=TEXT("6200","@"))*(MONTH('General Journal'!$C$10:$C$1809)>=$D$6)*(MONTH('General Journal'!$C$10:$C$1809)<=$H$6)*(ISNUMBER('General Journal'!$C$10:$C$1809))*'General Journal'!$H$10:$H$1809),0) -> 0 | G52: =IFERROR(SUMPRODUCT((TEXT('General Journal'!$E$10:$E$1809,"@")=TEXT("6200","@"))*(MONTH('General Journal'!$C$10:$C$1809)>=$D$6)*(MONTH('General Journal'!$C$10:$C$1809)<=$H$6)*(ISNUMBER('General Journal'!$C$10:$C$1809))*'General Journal'!$I$10:$I$1809),0) -> 0 | H52: =F52-G52 -> 0
B53: 6300 | C53: Interest Expense | D53: Expense | E53: Debit | F53: =IFERROR(SUMPRODUCT((TEXT('General Journal'!$E$10:$E$1809,"@")=TEXT("6300","@"))*(MONTH('General Journal'!$C$10:$C$1809)>=$D$6)*(MONTH('General Journal'!$C$10:$C$1809)<=$H$6)*(ISNUMBER('General Journal'!$C$10:$C$1809))*'General Journal'!$H$10:$H$1809),0) -> 0 | G53: =IFERROR(SUMPRODUCT((TEXT('General Journal'!$E$10:$E$1809,"@")=TEXT("6300","@"))*(MONTH('General Journal'!$C$10:$C$1809)>=$D$6)*(MONTH('General Journal'!$C$10:$C$1809)<=$H$6)*(ISNUMBER('General Journal'!$C$10:$C$1809))*'General Journal'!$I$10:$I$1809),0) -> 0 | H53: =F53-G53 -> 0
B54: 6400 | C54: Other Expenses | D54: Expense | E54: Debit | F54: =IFERROR(SUMPRODUCT((TEXT('General Journal'!$E$10:$E$1809,"@")=TEXT("6400","@"))*(MONTH('General Journal'!$C$10:$C$1809)>=$D$6)*(MONTH('General Journal'!$C$10:$C$1809)<=$H$6)*(ISNUMBER('General Journal'!$C$10:$C$1809))*'General Journal'!$H$10:$H$1809),0) -> 0 | G54: =IFERROR(SUMPRODUCT((TEXT('General Journal'!$E$10:$E$1809,"@")=TEXT("6400","@"))*(MONTH('General Journal'!$C$10:$C$1809)>=$D$6)*(MONTH('General Journal'!$C$10:$C$1809)<=$H$6)*(ISNUMBER('General Journal'!$C$10:$C$1809))*'General Journal'!$I$10:$I$1809),0) -> 0 | H54: =F54-G54 -> 0
B56: TRIAL BALANCE TOTALS — ============================== | F56: =SUM(F12:F54) -> 0 | G56: =SUM(G12:G54) -> 0 | H56: =IF(F56=G56,"✔ BALANCED","✖ CHECK JOURNAL") -> ✔ BALANCED

Sheet Income Statement
B2: INCOME STATEMENT
B3: Auto-populated by macro from Trial Balance | Verify after running macro
B4: Period: | C4: ='General Ledger & Trial Balance'!E5 -> 0
B6: Account | C6: Amount (₱) | D6: Notes
B7: REVENUE
B8: Sales Revenue | D8: Acct #4000
B9: Service Revenue | D9: Acct #4100
B10: Interest Income | D10: Acct #4200
B11: Other Income | D11: Acct #4300
B12: GROSS REVENUE | C12: =IFERROR(SUM(C8:C11),0) -> 0
B14: COST OF GOODS SOLD
B15: Cost of Goods Sold | D15: Acct #5000
B16: GROSS PROFIT | C16: =IFERROR(C12-C15,0) -> 0
B18: OPERATING EXPENSES
B19: Advertising & Marketing | D19: Acct #5100
B20: Bank Charges & Fees | D20: Acct #5200
B21: Depreciation Expense | D21: Acct #5300
B22: Insurance Expense | D22: Acct #5400
B23: Office Supplies Expense | D23: Acct #5500
B24: Professional Fees | D24: Acct #5600
B25: Rent Expense | D25: Acct #5700
B26: Salaries & Wages | D26: Acct #5800
B27: Taxes & Licenses | D27: Acct #5900
B28: Travel & Entertainment | D28: Acct #6000
B29: Utilities Expense | D29: Acct #6100
B30: Other Expenses | D30: Acct #6400
B31: TOTAL OPERATING EXPENSES | C31: =IFERROR(SUM(C19:C30),0) -> 0
B33: OPERATING INCOME (EBIT) | C33: =IFERROR(C16-C31,0) -> 0
B35: OTHER INCOME / (EXPENSE)
B36: Interest Expense | D36: Acct #6300
B37: NET OTHER INCOME/(EXPENSE) | C37: =IFERROR(-C36,0) -> 0
B39: INCOME BEFORE TAX | C39: =IFERROR(C33+C37,0) -> 0
B40: Income Tax Expense | D40: Acct #6200
B41: NET INCOME / (LOSS) | C41: =IFERROR(C39-C40,0) -> 0

Sheet Balance Sheet
B2: BALANCE SHEET
B3: Cumulative balances as of period end | Balance Sheet is always shown on a cumulative basis
B4: As of: | C4: ='General Ledger & Trial Balance'!E5 -> 0
B6: Account | C6: Amount (₱) | D6: Acct #
B7: ASSETS
B8: Current Assets
B9: Cash and Cash Equivalents | D9: #1000
B10: Petty Cash | D10: #1010
B11: Accounts Receivable | D11: #1100
B12: Less: Allowance for Doubtful Accts | D12: #1110
B13: Inventory | D13: #1200
B14: Prepaid Expenses | D14: #1300
B15: Short-term Investments | D15: #1400
B16: TOTAL CURRENT ASSETS | C16: =IFERROR(SUM(C9:C15),0) -> 0
B18: Non-Current Assets
B19: Property, Plant & Equipment | D19: #1500
B20: Less: Accumulated Depreciation | D20: #1510
B21: Intangible Assets | D21: #1600
B22: Less: Accumulated Amortization | D22: #1610
B23: Other Long-term Assets | D23: #1700
B24: TOTAL NON-CURRENT ASSETS | C24: =IFERROR(SUM(C19:C23),0) -> 0
B26: TOTAL ASSETS | C26: =IFERROR(C16+C24,0) -> 0
B28: LIABILITIES
B29: Current Liabilities
B30: Accounts Payable | D30: #2000
B31: Accrued Liabilities | D31: #2100
B32: Salaries Payable | D32: #2200
B33: Taxes Payable | D33: #2300
B34: Unearned Revenue | D34: #2400
B35: Notes Payable - Current | D35: #2500
B36: TOTAL CURRENT LIABILITIES | C36: =IFERROR(SUM(C30:C35),0) -> 0
B38: Non-Current Liabilities
B39: Long-term Debt | D39: #2600
B40: Deferred Tax Liability | D40: #2700
B41: TOTAL NON-CURRENT LIABILITIES | C41: =IFERROR(SUM(C39:C40),0) -> 0
B43: TOTAL LIABILITIES | C43: =IFERROR(C36+C41,0) -> 0
B45: EQUITY
B46: Owner's Capital / Common Stock | D46: #3000
B47: Retained Earnings | D47: #3100
B48: Additional Paid-in Capital | D48: #3200
B49: Less: Owner's Drawings | D49: #3300
B50: Current Period Net Income | C50: ='Income Statement'!C41 -> 0
B51: TOTAL EQUITY | C51: =IFERROR(SUM(C46:C50),0) -> 0
B53: TOTAL LIABILITIES + EQUITY | C53: =IFERROR(C43+C51,0) -> 0
B55: BALANCE CHECK | C55: =IF(C26=C53,"✔ BALANCED (Assets = Liabilities + Equity)","✖ DOES NOT BALANCE — check journal entries") -> ✔ BALANCED (Assets = Liabilities + Equity)

Sheet Cash Flow Statement
B2: CASH FLOW STATEMENT (Indirect Method)
B3: Auto-populated by macro | Operating / Investing / Financing Activities
B4: Period: | C4: ='General Ledger & Trial Balance'!E5 -> 0
B6: Description | C6: Amount (₱) | D6: Source
B7: OPERATING ACTIVITIES
B8: Net Income (from Income Statement) | C8: ='Income Statement'!C41 -> 0
B9: Adjustments to reconcile Net Income:
B10: Add: Depreciation & Amortization | D10: #5300
B11: Add/Less: Changes in Working Capital
B12: (Increase)/Decrease in A/R | D12: #1100
B13: (Increase)/Decrease in Inventory | D13: #1200
B14: (Increase)/Decrease in Prepaid Exp | D14: #1300
B15: Increase/(Decrease) in A/P | D15: #2000
B16: Increase/(Decrease) in Accrued Liab | D16: #2100
B17: Increase/(Decrease) in Unearned Rev | D17: #2400
B18: NET CASH FROM OPERATING ACTIVITIES | C18: =IFERROR(SUM(C8:C17),0) -> 0
B20: INVESTING ACTIVITIES
B21: Purchase of PP&E | D21: #1500
B22: Purchase of Investments | D22: #1400
B23: Proceeds from sale of assets
B24: NET CASH FROM INVESTING ACTIVITIES | C24: =IFERROR(SUM(C21:C23),0) -> 0
B26: FINANCING ACTIVITIES
B27: Proceeds from borrowings | D27: #2600
B28: Repayment of loans | D28: #2600
B29: Owner contributions | D29: #3000
B30: Owner drawings / Dividends | D30: #3300
B31: NET CASH FROM FINANCING ACTIVITIES | C31: =IFERROR(SUM(C27:C30),0) -> 0
B33: NET INCREASE/(DECREASE) IN CASH | C33: =IFERROR(C18+C24+C31,0) -> 0
B34: Beginning Cash Balance
B35: ENDING CASH BALANCE | C35: =IFERROR(C34+C33,0) -> 0

Sheet Dashboard
B2: ACCOUNTING SYSTEM DASHBOARD
B3: Real-time summary linked from all sheets | Run macro on Trial Balance to generate Financial Statements
B4: Period: | E4: ='General Ledger & Trial Balance'!E5 -> 0
B6: QUICK FINANCIAL SUMMARY | G6: SYSTEM GUIDE
B7: Total Revenue | C7: ='Income Statement'!C12 -> 0 | G7: 1. Start in Chart of Accounts — review/add accounts
B8: Total Expenses | C8: ='Income Statement'!C31 -> 0 | G8: 2. Enter transactions in General Journal (double-entry)
B9: Net Income | C9: ='Income Statement'!C41 -> 0 | G9: 3. General Ledger auto-tallies all accounts via SUMIF
B10: Total Assets | C10: ='Balance Sheet'!C26 -> 0 | G10: 4. Go to Trial Balance → click MACRO BUTTON
B11: Total Liabilities | C11: ='Balance Sheet'!C43 -> 0 | G11: 5. Macro populates Income Statement, Balance Sheet & Cash Flow
B12: Total Equity | C12: ='Balance Sheet'!C51 -> 0 | G12: 6. Review Income Tax Table for 2025 tax planning
B13: Net Cash from Operations | C13: ='Cash Flow Statement'!C18 -> 0 | G13: 7. Save as .xlsm to enable the macro button
B14: Trial Balance Status | C14: ='General Ledger & Trial Balance'!H53 -> 0 | G14: 8. Blue text = input | Black = formula | Green = cross-sheet link
B16: ★ To activate macro: ALT+F11 > Import GenerateFinancialStatements.bas > Save as .xlsm > Assign to button

Sheet Income Tax Table 2025
B2: PHILIPPINE INCOME TAX REFERENCE TABLE — 2025 (TRAIN Law & CREATE Act)
B3: Bureau of Internal Revenue (BIR) | RA 10963 (TRAIN Law) | RA 11534 (CREATE Act) | RA 11975 (CREATE MORE) | RA 12214 (CMEPA 2025)
B5: SECTION 1 — INDIVIDUAL INCOME TAX: GRADUATED RATES (TRAIN Law Schedule 2 — effective 2023 onwards)
B6: Applies to: Compensation Earners | Self-Employed/Professionals with gross receipts > ₱3M | Those who OPTED OUT of 8% flat tax
B7: Annual Taxable Income Bracket | C7: Base Tax (₱) | D7: Rate on Excess | E7: Tax at Upper Limit | F7: Notes
B8: ₱0 – ₱250,000 | C8: — | D8: EXEMPT | E8: — | F8: EXEMPT — zero income tax due
B9: ₱250,001 – ₱400,000 | C9: ₱0 | D9: 15% | E9: ₱22,500 | F9: 15% on excess over ₱250,000
B10: ₱400,001 – ₱800,000 | C10: ₱22,500 | D10: 20% | E10: ₱102,500 | F10: ₱22,500 + 20% on excess over ₱400,000
B11: ₱800,001 – ₱2,000,000 | C11: ₱102,500 | D11: 25% | E11: ₱402,500 | F11: ₱102,500 + 25% on excess over ₱800,000
B12: ₱2,000,001 – ₱8,000,000 | C12: ₱402,500 | D12: 30% | E12: ₱2,202,500 | F12: ₱402,500 + 30% on excess over ₱2,000,000
B13: Over ₱8,000,000 | C13: ₱2,202,500 | D13: 35% | E13: No limit | F13: ₱2,202,500 + 35% on excess over ₱8,000,000
B15: SECTION 2 — 8% FLAT INCOME TAX RATE OPTION (Self-Employed & Professionals)
B16: Available ONLY to self-employed individuals & professionals with gross sales/receipts NOT exceeding the ₱3,000,000 VAT threshold
B17: Condition | C17: Rate | D17: Tax Base | E17: Exemption | F17: Remarks
B18: Gross sales/receipts ≤ ₱3,000,000 | C18: 8% | D18: Gross Sales/Receipts − ₱250,000 | E18: ₱250,000 exempt | F18: In lieu of graduated income tax AND 3% percentage tax
B19: Gross sales/receipts > ₱3,000,000 | C19: Not eligible | D19: Must use graduated rates | E19: N/A | F19: Automatically subject to graduated rates + 12% VAT
B20: Mixed income earner (employment + business) | C20: 8% on business only | D20: Business/professional income only | E20: ₱250,000 exempt | F20: Compensation income still taxed under graduated rates
B21: Election of 8% option | C21: Irrevocable for taxable year | D21: Filed on 1st quarter BIR Form 1701Q | E21: N/A | F21: Revocable only on the next taxable year
B23: SECTION 3 — CORPORATE INCOME TAX (CREATE Act RA 11534 | CREATE MORE RA 11975 effective 2025)
B24: Corporation Type | C24: CIT Rate | D24: Basis | E24: MCIT | F24: Remarks
B25: Domestic Corporations (Regular) | C25: 25% | D25: Net Taxable Income | E25: 2% of Gross Income (from 4th year of operations) | F25: Standard rate; MCIT applies if higher than regular CIT
B26: MSMEs (net taxable income ≤ ₱5M AND assets ≤ ₱100M excl. land) | C26: 20% | D26: Net Taxable Income | E26: 2% MCIT also applies | F26: Reduced rate under CREATE Act; must meet BOTH thresholds
B27: Proprietary Educational Institutions / Hospitals | C27: 10% | D27: Net Taxable Income | E27: N/A | F27: Provided ≤ 50% of gross income is from unrelated trade
B28: Non-Profit / Tax-Exempt Corporations | C28: Exempt | D28: Qualifying income only | E28: N/A | F28: Unrelated business income taxable at 25%; requires BIR ruling
B29: Resident Foreign Corporations (RFC) | C29: 25% | D29: Net Taxable Income (PH-sourced only) | E29: 2% MCIT | F29: Same treatment as domestic corps under CREATE Act
B30: Non-Resident Foreign Corporations (NRFC) | C30: 25% | D30: Gross Income (PH-sourced only) | E30: None | F30: No MCIT; subject to final withholding tax by payor
B31: CREATE MORE — Enhanced Deductions Regime | C31: 20% | D31: Registered activity income only | E31: N/A | F31: RA 11975; for FIRB/IPA-registered entities effective 2025
B32: Branch Profit Remittance Tax | C32: 15% | D32: Total profits remitted abroad | E32: N/A | F32: Applied on profits remitted by branch to foreign parent
B34: SECTION 4 — VALUE ADDED TAX (VAT) & PERCENTAGE TAX
B35: Tax Type | C35: Rate | D35: Threshold / Coverage | E35: Filing | F35: Remarks
B36: VAT — Standard Rate | C36: 12% | D36: Gross sales/receipts > ₱3,000,000/year | E36: Monthly BIR 2550M + Quarterly BIR 2550Q | F36: Input VAT creditable against output VAT
B37: VAT — Zero-Rated | C37: 0% | D37: Exports, PEZA-registered entities, specific services | E37: Same as standard VAT returns | F37: Seller entitled to input VAT refund or credit
B38: VAT — Exempt Transactions | C38: Exempt | D38: Basic goods (raw food), education, health, books, etc. | E38: No VAT filing on exempt sales | F38: Cannot claim input VAT on purchases relating to exempt sales
B39: Percentage Tax (Non-VAT) | C39: 3% | D39: Gross receipts ≤ ₱3,000,000/year | E39: Quarterly BIR 2551Q | F39: In lieu of VAT; no input VAT credits available
B40: Digital Services VAT — RA 12023 | C40: 12% | D40: Non-resident digital service providers (PH-consumed services) | E40: Withholding by VAT-registered buyers; monthly remittance | F40: Effective June 2, 2025 — streaming, cloud, online platforms
B42: SECTION 5 — KEY WITHHOLDING TAX RATES (Creditable & Final)
B43: Income Payment Type | C43: WHT Rate | D43: Type | E43: BIR Form | F43: Remarks
B44: Professional fees — Individuals | C44: 10% / 15% | D44: Creditable | E44: 1601-EQ | F44: 10% if gross income ≤ ₱3M/yr; 15% if > ₱3M/yr
B45: Professional fees — Juridical persons | C45: 15% | D45: Creditable | E45: 1601-EQ | F45: Standard EWT rate for companies
B46: Rentals — real property | C46: 5% | D46: Creditable | E46: 1601-EQ | F46: On gross rental payments to individual or entity
B47: Interest on bank deposits (regular PH peso) | C47: 20% | D47: Final | E47: 1601-FQ | F47: Flat 20% FWT; updated under CMEPA 2025
B48: Interest on FCDU / expanded FCDU deposits | C48: 15% | D48: Final | E48: 1601-FQ | F48: Foreign currency deposit unit interest
B49: Dividends — to resident individual | C49: 10% | D49: Final | E49: 1601-FQ | F49: Paid by domestic corp to resident individual shareholder
B50: Dividends — to non-resident alien | C50: 25% | D50: Final | E50: 1601-FQ | F50: May be reduced under applicable PH tax treaty
B51: Royalties — books & literary works | C51: 10% | D51: Final | E51: 1601-FQ | F51: Preferential rate for books, literary and musical works
B52: Royalties — patents, trademarks, etc. | C52: 20% | D52: Final | E52: 1601-FQ | F52: Standard rate for all other royalties
B53: Prizes exceeding ₱10,000 | C53: 20% | D53: Final | E53: 1601-FQ | F53: Prizes ≤ ₱10,000 subject to graduated income tax
B54: Capital Gains Tax — Real Property (individual) | C54: 6% | D54: Final | E54: 1706 | F54: Based on higher of selling price or BIR zonal value
... B58: 13th Month Pay & Bonuses — exempt portion | C58: EXEMPT | D58: — | E58: 2316 | F58: Tax-free up to ₱90,000/year; excess subject to WHT
B60: SECTION 6 — DOCUMENTARY STAMP TAX (DST) — Selected Key Rates
B61: Document / Transaction | C61: DST Rate | D61: Basis | E61: BIR Form | F61: Notes
B62: Original Issuance of Shares | C62: ₱2.00 per ₱200 par value | D62: Par value of shares issued | E62: BIR 2000 | F62: Effective rate: 1% of par value
B63: Sale / Transfer of Shares (unlisted) — CMEPA | C63: ₱0.75 per ₱200 | D63: Par value or actual consideration | E63: BIR 2000 | F63: Reduced from 1% to 0.75% under CMEPA 2025
B64: Loan Agreements / Promissory Notes | C64: ₱1.00 per ₱200 | D64: Face amount of instrument | E64: BIR 2000 | F64: Effective rate: 0.5% of face value
B65: Deeds of Sale — Real Property | C65: ₱15.00 per ₱1,000 | D65: Higher of consideration or BIR zonal value | E65: BIR 2000 | F65: Effective rate: 1.5%
B66: Mortgages / Pledges | C66: ₱20 per first ₱5,000 + ₱10 per add'l ₱5,000 | D66: Amount secured by instrument | E66: BIR 2000 | F66: Sliding scale applied on total secured amount
B67: Lease Agreements | C67: ₱3.00 per ₱2,000 per year | D67: Annual rental amount | E67: BIR 2000 | F67: Charged per year of the lease term
B68: Life Insurance Policies (≤ ₱100K face value) | C68: ₱50 flat | D68: Face amount of policy | E68: BIR 2000 | F68: Higher amounts: ₱0.50 per ₱200 face value
B70: SECTION 7 — BIR FILING DEADLINES (Annual Reference)
B71: Tax Return | C71: BIR Form | D71: Frequency | E71: Deadline | F71: Penalty for Late Filing
B72: Annual ITR — Individual (compensation only) | C72: 1701A | D72: Annual | E72: April 15 of following year | F72: 25% surcharge + 12% interest p.a. + compromise penalty
B73: Annual ITR — Individual (with business/professional income) | C73: 1701 | D73: Annual | E73: April 15 of following year | F73: Same as above
B74: Annual ITR — Corporation | C74: 1702 | D74: Annual | E74: April 15 (calendar year); 60 days after fiscal year end | F74: 25% surcharge + 12% interest p.a.
B75: Quarterly ITR — Individual | C75: 1701Q | D75: Quarterly | E75: May 15 / Aug 15 / Nov 15 | F75: 25% surcharge + 12% interest p.a.
B76: Quarterly ITR — Corporation | C76: 1702Q | D76: Quarterly | E76: 60 days after close of each quarter | F76: Same as above
B77: Monthly VAT Return | C77: 2550M | D77: Monthly | E77: 25th of following month | F77: 25% surcharge + 12% interest p.a.
B78: Quarterly VAT Return | C78: 2550Q | D78: Quarterly | E78: 25th day after quarter close | F78: Same as monthly VAT
B79: Quarterly Percentage Tax | C79: 2551Q | D79: Quarterly | E79: 25th day after quarter close | F79: 25% surcharge + interest
B80: Monthly WHT — Compensation | C80: 1601C | D80: Monthly | E80: 10th or 15th of following month (eFPS) | F80: 25% surcharge + interest
B81: Quarterly Final / Creditable WHT | C81: 1601-EQ / 1601-FQ | D81: Quarterly | E81: Last day of month after quarter end | F81: 25% surcharge + interest
B82: Annual Alphalist / Information Return | C82: 1604C / 1604E / 1604F | D82: Annual | E82: January 31 of following year | F82: ₱1,000–₱25,000 per return
B83: Certificate of Compensation — per employee | C83: 2316 | D83: Annual / Upon separation | E83: January 31 or date of separation | F83: ₱1,000–₱25,000 per employee
B85: SECTION 8 — QUICK TAX COMPUTATION GUIDE
B86: Formula: Tax Due = Base Tax + (Taxable Income − Lower Bracket Limit) × Rate on Excess
B87: Graduated Example: Taxable income ₱600,000 → ₱22,500 + (₱600,000 − ₱400,000) × 20% = ₱22,500 + ₱40,000 = ₱62,500 income tax
B88: 8% Option Example: Gross receipts ₱1,500,000 → (₱1,500,000 − ₱250,000) × 8% = ₱100,000 income tax (replaces both income tax + percentage tax)
B90: ⚠ DISCLAIMER & SOURCES: Rates based on TRAIN Law (RA 10963), CREATE Act (RA 11534), CREATE MORE Act (RA 11975), Ease of Paying Taxes Act (RA 11976), and CMEPA (RA 12214). Digital Services VAT from RA 12023 effective June 2, 2025. Always verify current rates at www.bir.gov.ph before filing. This table is for general reference only and does not constitute legal or tax advice. Consult a licensed CPA or BIR-accredited tax practitioner for advice specific to your situation.

Sheet Income Tax Calculator
B2: 🇵🇭 PHILIPPINE INCOME TAX CALCULATOR | 2025 (TRAIN Law & CREATE Act)
B3: Select taxpayer type below | Enter income figures in BLUE cells | Tax computed automatically
B5: STEP 1 — SELECT TAXPAYER TYPE: | D5: Individual (Compensation)
B6: STEP 2 — 8% FLAT TAX OPTION (Self-Employed / Mixed Income only): | D6: No (Use Graduated Rates)
B7: =IF(OR(D5="Individual (Self-Employed / Professional)",D5="Individual (Mixed Income)"),"ℹ 8% option available — requires gross receipts ≤ ₱3,000,000. If elected, it replaces graduated rates AND percentage tax.","ℹ 8% flat tax option is only available to Self-Employed / Professional or Mixed Income individuals.") -> ℹ 8% flat tax option is only available to Self-Employed / Professional or Mixed Income individuals.
B9: STEP 3 — ENTER INCOME & DEDUCTION FIGURES
B10: INDIVIDUAL — COMPENSATION INCOME
B11: Gross Compensation Income | F11: Annual gross salary before deductions
B12: Less: SSS / GSIS Contributions | F12: Mandatory contributions (deductible)
B13: Less: PhilHealth Contributions | F13: Mandatory contributions (deductible)
B14: Less: Pag-IBIG Contributions | F14: Mandatory contributions (deductible)
B15: Less: 13th Month Pay / Bonuses (exempt portion) | F15: Max ₱90,000 exempt
B16: Less: Other Non-Taxable Benefits | F16: De minimis etc.
B17: TAXABLE COMPENSATION INCOME | D17: =MAX(0,C11-C12-C13-C14-C15-C16) -> 0 | F17: Gross less all deductions
B19: INDIVIDUAL — BUSINESS / PROFESSIONAL INCOME (Self-Employed or Mixed)
B20: Gross Sales / Professional Receipts | F20: Total gross for the period
B21: Less: Cost of Sales / Direct Costs | F21: COGS or direct service costs
B22: Less: Allowable Business Deductions | F22: Operating expenses, depreciation etc.
B23: NET BUSINESS / PROFESSIONAL INCOME | D23: =MAX(0,C20-C21-C22) -> 0 | F23: Gross less costs & deductions
B25: PARTNERSHIP / CORPORATION — TAXABLE INCOME
B26: Gross Revenue / Sales | F26: Total gross income
B27: Less: Cost of Sales | F27: COGS
B28: Less: Allowable Deductions | F28: Operating expenses, depreciation etc.
B29: NET TAXABLE INCOME | D29: =MAX(0,C26-C27-C28) -> 0 | F29: Gross less all deductions
B30: Gross Income (for MCIT computation) | F30: Gross Revenue less Cost of Sales only
B32: STEP 4 — INCOME TAX COMPUTATION
B33: Applicable Taxable Income / Gross Receipts | D33: =IF(D5="Individual (Compensation)",C17,IF(OR(D5="Individual (Self-Employed / Professional)",D5="Individual (Mixed Income)"),IF(D6="Yes (Avail 8% Flat Tax)",C20,C23),C29)) -> 0 | F33: Auto-selected based on taxpayer type above
B34: GRADUATED INCOME TAX COMPUTATION (TRAIN Law Schedule 2)
B35: Income Bracket | C35: Lower Limit | D35: Base Tax | E35: Rate | F35: Tax in Bracket
B36: ₱0 – ₱250,000 (0% / Exempt) | C36: 0 | D36: 0 | E36: 0 | F36: =IF(D33>0,0,0) -> 0
B37: ₱250,001 – ₱400,000 (15%) | C37: 250000 | D37: 0 | E37: 0.15 | F37: =IF(D33<=250000,0,IF(D33>=400000,(400000-250000)*0.15,(D33-250000)*0.15)) -> 0
B38: ₱400,001 – ₱800,000 (20%) | C38: 400000 | D38: 22500 | E38: 0.2 | F38: =IF(D33<=400000,0,IF(D33>=800000,(800000-400000)*0.2,(D33-400000)*0.2)) -> 0
B39: ₱800,001 – ₱2,000,000 (25%) | C39: 800000 | D39: 102500 | E39: 0.25 | F39: =IF(D33<=800000,0,IF(D33>=2000000,(2000000-800000)*0.25,(D33-800000)*0.25)) -> 0
B40: ₱2,000,001 – ₱8,000,000 (30%) | C40: 2000000 | D40: 402500 | E40: 0.3 | F40: =IF(D33<=2000000,0,IF(D33>=8000000,(8000000-2000000)*0.3,(D33-2000000)*0.3)) -> 0
B41: Over ₱8,000,000 (35%) | C41: 8000000 | D41: 2202500 | E41: 0.35 | F41: =IF(D33<=8000000,0,(D33-8000000)*0.35) -> 0
B42: TOTAL GRADUATED INCOME TAX | F42: =SUM(F36:F41) -> 0
B44: 8% FLAT INCOME TAX OPTION (Self-Employed / Professional — Gross Receipts ≤ ₱3,000,000)
B45: Gross Sales / Professional Receipts | D45: =C20 -> 0 | F45: Pulled from income input above
B46: Less: ₱250,000 Exempt Amount | D46: 250000 | F46: Standard exempt amount per TRAIN Law
B47: Net Tax Base (Gross Receipts − ₱250,000) | D47: =MAX(0,D45-D46) -> 0
B48: × 8% Flat Tax Rate | D48: 0.08
B49: TOTAL 8% FLAT TAX | F49: =D47*D48 -> 0
B51: CORPORATE / PARTNERSHIP INCOME TAX (Regular CIT & MCIT)
B52: Applicable CIT Rate (based on taxpayer type) | D52: =IF(D5="Corporation (MSME - 20%)",0.2,IF(D5="Corporation (Proprietary School/Hospital - 10%)",0.1,IF(D5="Corporation (CREATE MORE - 20%)",0.2,IF(D5="Partnership",0.25,0.25)))) -> 0.25 | F52: Auto-selected: 25% regular / 20% MSME or CREATE MORE / 10% School
B53: Regular CIT (Net Taxable Income × CIT Rate) | D53: =C29*D52 -> 0 | F53: Regular CIT
B54: MCIT (Gross Income × 2%) | D54: =C30*0.02 -> 0 | F54: MCIT applies from 4th year of operations
B55: MCIT Applicable? (from 4th year of operations) | D55: No | F55: Select Yes if company is in 4th year or beyond
B56: TOTAL CORPORATE / PARTNERSHIP TAX | F56: =IF(D55="Yes",MAX(D53,D54),D53) -> 0
B58: STEP 5 — INCOME TAX DUE SUMMARY
B59: Taxpayer Type | D59: =D5 -> Individual (Compensation)
B60: 8% Option Elected? | D60: =D6 -> No (Use Graduated Rates)
B61: Taxable Income / Tax Base Used | D61: =D33 -> 0 | F61: Auto-selected based on taxpayer type
B63: INCOME TAX DUE | D63: =IF(OR(D5="Partnership",D5="Corporation (Regular - 25%)",D5="Corporation (MSME - 20%)",D5="Corporation (Proprietary School/Hospital - 10%)",D5="Corporation (CREATE MORE - 20%)"),F56,IF(D6="Yes (Avail 8% Flat Tax)",F49,IF(D5="Individual (Compensation)",F42,IF(D5="Individual (Mixed Income)",F42+F49,F42)))) -> 0 | F63: Final tax due per BIR return
B65: Effective Tax Rate | D65: =IFERROR(D63/IF(D61=0,1,D61),0) -> 0 | F65: Tax Due ÷ Taxable Income
B66: Less: Creditable Withholding Tax (CWT) | F66: Enter total CWT certificates (BIR Form 2307)
B67: Less: Prior Quarter Tax Payments | F67: Quarterly payments already remitted
B68: TAX STILL DUE / (OVERPAYMENT) | D68: =D63-IF(D66="",0,D66)-IF(D67="",0,D67) -> 0 | F68: (Negative = refundable overpayment)
B70: =IF(D6="Yes (Avail 8% Flat Tax)","✔ 8% Flat Tax elected — Percentage Tax (3%) is WAIVED. No need to file BIR 2551Q for business income.",IF(OR(D5="Individual (Self-Employed / Professional)",D5="Individual (Mixed Income)"),"⚠ Graduated rates used — you must also pay 3% Percentage Tax on gross receipts (BIR Form 2551Q) quarterly.",""))
B72: =IF(D5="Individual (Compensation)","BIR Form: 1701A (Compensation) — Annual ITR due April 15",IF(D5="Individual (Self-Employed / Professional)","BIR Form: 1701 (Self-Employed) — Annual ITR due April 15 | Quarterly: 1701Q",IF(D5="Individual (Mixed Income)","BIR Form: 1701 (Mixed Income) — Annual ITR due April 15 | Quarterly: 1701Q",IF(OR(D5="Corporation (Regular - 25%)",D5="Corporation (MSME - 20%)",D5="Corporation (CREATE MORE - 20%)",D5="Corporation (Proprietary School/Hospital - 10%)"),"BIR Form: 1702 (Corporation) — Annual ITR | Quarterly: 1702Q due 60 days after each quarter","BIR Form: 1702 (Partnership) — Annual ITR due April 15 | Quarterly: 1702Q")))) -> BIR Form: 1701A (Compensation) — Annual ITR due April 15
B74: ⚠ DISCLAIMER: This calculator is for estimation purposes only based on TRAIN Law (RA 10963) and CREATE Act (RA 11534) rates. It does not account for all BIR-specific rules, special deductions, tax treaty benefits, or audit adjustments. Computed figures should not be used as final tax returns without review by a licensed CPA. Always file official BIR returns and verify rates at www.bir.gov.ph.
